{
  "attached": {
    "entity_components": {},
    "on_cast": [
      {
        "acts": [
          {
            "type": "summon_pet",
            "map": {
              "count": 1.0,
              "entity_name": "default_entity_name",
              "life_ticks": 600.0,
              "summon_id": "mmorpg:spirit_wolf"
            }
          }
        ],
        "en_preds": [],
        "ifs": [
          {
            "type": "on_spell_cast",
            "map": {}
          }
        ],
        "targets": []
      },
      {
        "acts": [
          {
            "type": "particles_in_radius",
            "map": {
              "motion": "None",
              "particle_count": 200.0,
              "particle_type": "minecraft:witch",
              "radius": 3.5
            }
          }
        ],
        "en_preds": [],
        "ifs": [
          {
            "type": "on_spell_cast",
            "map": {}
          }
        ],
        "targets": []
      },
      {
        "acts": [
          {
            "type": "particles_in_radius",
            "map": {
              "motion": "None",
              "particle_count": 200.0,
              "particle_type": "minecraft:soul",
              "radius": 3.5
            }
          }
        ],
        "en_preds": [],
        "ifs": [
          {
            "type": "on_spell_cast",
            "map": {}
          }
        ],
        "targets": []
      },
      {
        "acts": [
          {
            "type": "sound",
            "map": {
              "pitch": 1.0,
              "sound": "minecraft:entity.evoker.prepare_summon",
              "volume": 0.5
            }
          }
        ],
        "en_preds": [],
        "ifs": [
          {
            "type": "on_spell_cast",
            "map": {}
          }
        ],
        "targets": []
      }
    ]
  },
  "config": {
    "apply_cast_speed_to_cd": false,
    "cast_time_ticks": 30,
    "castingWeapon": "ANY_WEAPON",
    "charge_name": "",
    "charge_regen": 0,
    "charges": 0,
    "cooldown_ticks": 600,
    "ene_cost": {
      "max": 0.0,
      "min": 0.0
    },
    "imbues": 0,
    "mana_cost": {
      "max": 22.5,
      "min": 30.0
    },
    "style": "int",
    "summonType": "BEAST",
    "summon_basic_atk": "pet_basic",
    "swing_arm": true,
    "tags": [
      "summon",
      "damage",
      "beast",
      "has_pet_ability"
    ],
    "times_to_cast": 1,
    "tracking_radius": 5
  },
  "default_lvl": 0,
  "disabled_dims": [],
  "effect_tip": "",
  "identifier": "summon_spirit_wolf",
  "loc_name": "Summon Spirit Wolf",
  "manual_tip": true,
  "max_lvl": 16,
  "min_lvl": 1,
  "statsForSkillGem": [
    {
      "type": "FLAT",
      "max": 25.0,
      "min": 5.0,
      "stat": "summon_damage"
    },
    {
      "type": "FLAT",
      "max": 300.0,
      "min": 30.0,
      "stat": "summon_health"
    }
  ],
  "weight": 1000
}